tq/__init__.py
tq1-0.4.6.dist-info/LICENSE
tq1-0.4.6.dist-info/METADATA
tq1-0.4.6.dist-info/WHEEL
tq1-0.4.6.dist-info/entry_points.txt
tq1-0.4.6.dist-info/top_level.txt
tq1-0.4.6.dist-info/RECORD
