Metadata-Version: 2.1
Name: tq1
Version: 0.4.6
Summary: Simple Command Line Job Manager
Home-page: https://github.com/CDLuminate/tq
Author: Mo Zhou
Author-email: cdluminate@gmail.com
License: MIT
Platform: UNKNOWN
